buy_and_hold_vs_arima/__init__.py
buy_and_hold_vs_arima/_modidx.py
buy_and_hold_vs_arima/arima_implement.py
buy_and_hold_vs_arima/arima_stats.py
buy_and_hold_vs_arima/core.py
buy_and_hold_vs_arima/deploy_project.py
buy_and_hold_vs_arima/final_dash_product.py
buy_and_hold_vs_arima/thesis_app.py
buy_and_hold_vs_arima/thesis_ta35.py
buy_and_hold_vs_arima-0.0.14.dist-info/LICENSE
buy_and_hold_vs_arima-0.0.14.dist-info/METADATA
buy_and_hold_vs_arima-0.0.14.dist-info/WHEEL
buy_and_hold_vs_arima-0.0.14.dist-info/entry_points.txt
buy_and_hold_vs_arima-0.0.14.dist-info/top_level.txt
buy_and_hold_vs_arima-0.0.14.dist-info/RECORD
